MANIFEST.in
README.rst
requirements-test.txt
setup.py
rexpression/__init__.py
rexpression.egg-info/PKG-INFO
rexpression.egg-info/SOURCES.txt
rexpression.egg-info/dependency_links.txt
rexpression.egg-info/top_level.txt
rexpression.egg-info/zip-safe